{
  "문서정보": {
    "문서명": "거래실적증명서",
    "발급일자": "2024년 11월 12일"
  },
  "신청인": {
    "상호": "케이엠건설 주식회사",
    "사업자등록번호": "129-87-56340",
    "대표자": "오세훈",
    "연락처": "031-711-4520",
    "주소": "경기도 용인시 수지구 광교중앙로 338",
    "업태": "건설업",
    "종목": "건축공사"
  },
  "증명용도": {
    "용도": "공사 실적 증빙용",
    "제출처": "경기도시공사 계약심사팀"
  },
  "거래내역": [
    {
      "번호": "1",
      "일자": "2024-01-18",
      "품명": "레미콘 25-24-150",
      "수량": "32",
      "단가": "112,000",
      "금액": "3,584,000",
      "세액": "358,400"
    },
    {
      "번호": "2",
      "일자": "2024-02-22",
      "품명": "철근 SD400 D13",
      "수량": "18",
      "단가": "785,000",
      "금액": "14,130,000",
      "세액": "1,413,000"
    },
    {
      "번호": "3",
      "일자": "2024-03-28",
      "품명": "단열재 100T",
      "수량": "240",
      "단가": "18,500",
      "금액": "4,440,000",
      "세액": "444,000"
    },
    {
      "번호": "4",
      "일자": "2024-04-25",
      "품명": "석고보드 9.5T",
      "수량": "360",
      "단가": "7,200",
      "금액": "2,592,000",
      "세액": "259,200"
    },
    {
      "번호": "5",
      "일자": "2024-05-30",
      "품명": "레미콘 25-24-150",
      "수량": "45",
      "단가": "112,000",
      "금액": "5,040,000",
      "세액": "504,000"
    },
    {
      "번호": "6",
      "일자": "2024-06-27",
      "품명": "철근 SD400 D16",
      "수량": "22",
      "단가": "812,000",
      "금액": "17,864,000",
      "세액": "1,786,400"
    },
    {
      "번호": "7",
      "일자": "2024-07-25",
      "품명": "단열재 100T",
      "수량": "300",
      "단가": "18,500",
      "금액": "5,550,000",
      "세액": "555,000"
    },
    {
      "번호": "8",
      "일자": "2024-08-29",
      "품명": "방수시트 1.5T",
      "수량": "160",
      "단가": "26,500",
      "금액": "4,240,000",
      "세액": "424,000"
    },
    {
      "번호": "9",
      "일자": "2024-09-26",
      "품명": "석고보드 9.5T",
      "수량": "420",
      "단가": "7,200",
      "금액": "3,024,000",
      "세액": "302,400"
    },
    {
      "번호": "10",
      "일자": "2024-10-31",
      "품명": "레미콘 25-24-150",
      "수량": "38",
      "단가": "112,000",
      "금액": "4,256,000",
      "세액": "425,600"
    }
  ],
  "합계": {
    "수량": "1635",
    "금액": "64,720,000",
    "세액": "6,472,000"
  },
  "발급자": {
    "상호": "동서자재 주식회사",
    "사업자등록번호": "124-86-35177",
    "주소": "경기도 화성시 팔탄면 시청로 860",
    "연락처": "031-352-6700",
    "대표이사": "강현우"
  },
  "문서정보/문서명": "거래실적증명서",
  "문서정보/발급일자": "2024년 11월 12일",
  "신청인/상호": "케이엠건설 주식회사",
  "신청인/사업자등록번호": "129-87-56340",
  "신청인/대표자": "오세훈",
  "신청인/연락처": "031-711-4520",
  "신청인/주소": "경기도 용인시 수지구 광교중앙로 338",
  "신청인/업태": "건설업",
  "신청인/종목": "건축공사",
  "증명용도/용도": "공사 실적 증빙용",
  "증명용도/제출처": "경기도시공사 계약심사팀",
  "거래내역/행01/번호": "1",
  "거래내역/행01/일자": "2024-01-18",
  "거래내역/행01/품명": "레미콘 25-24-150",
  "거래내역/행01/수량": "32",
  "거래내역/행01/단가": "112,000",
  "거래내역/행01/금액": "3,584,000",
  "거래내역/행01/세액": "358,400",
  "거래내역/행02/번호": "2",
  "거래내역/행02/일자": "2024-02-22",
  "거래내역/행02/품명": "철근 SD400 D13",
  "거래내역/행02/수량": "18",
  "거래내역/행02/단가": "785,000",
  "거래내역/행02/금액": "14,130,000",
  "거래내역/행02/세액": "1,413,000",
  "거래내역/행03/번호": "3",
  "거래내역/행03/일자": "2024-03-28",
  "거래내역/행03/품명": "단열재 100T",
  "거래내역/행03/수량": "240",
  "거래내역/행03/단가": "18,500",
  "거래내역/행03/금액": "4,440,000",
  "거래내역/행03/세액": "444,000",
  "거래내역/행04/번호": "4",
  "거래내역/행04/일자": "2024-04-25",
  "거래내역/행04/품명": "석고보드 9.5T",
  "거래내역/행04/수량": "360",
  "거래내역/행04/단가": "7,200",
  "거래내역/행04/금액": "2,592,000",
  "거래내역/행04/세액": "259,200",
  "거래내역/행05/번호": "5",
  "거래내역/행05/일자": "2024-05-30",
  "거래내역/행05/품명": "레미콘 25-24-150",
  "거래내역/행05/수량": "45",
  "거래내역/행05/단가": "112,000",
  "거래내역/행05/금액": "5,040,000",
  "거래내역/행05/세액": "504,000",
  "거래내역/행06/번호": "6",
  "거래내역/행06/일자": "2024-06-27",
  "거래내역/행06/품명": "철근 SD400 D16",
  "거래내역/행06/수량": "22",
  "거래내역/행06/단가": "812,000",
  "거래내역/행06/금액": "17,864,000",
  "거래내역/행06/세액": "1,786,400",
  "거래내역/행07/번호": "7",
  "거래내역/행07/일자": "2024-07-25",
  "거래내역/행07/품명": "단열재 100T",
  "거래내역/행07/수량": "300",
  "거래내역/행07/단가": "18,500",
  "거래내역/행07/금액": "5,550,000",
  "거래내역/행07/세액": "555,000",
  "거래내역/행08/번호": "8",
  "거래내역/행08/일자": "2024-08-29",
  "거래내역/행08/품명": "방수시트 1.5T",
  "거래내역/행08/수량": "160",
  "거래내역/행08/단가": "26,500",
  "거래내역/행08/금액": "4,240,000",
  "거래내역/행08/세액": "424,000",
  "거래내역/행09/번호": "9",
  "거래내역/행09/일자": "2024-09-26",
  "거래내역/행09/품명": "석고보드 9.5T",
  "거래내역/행09/수량": "420",
  "거래내역/행09/단가": "7,200",
  "거래내역/행09/금액": "3,024,000",
  "거래내역/행09/세액": "302,400",
  "거래내역/행10/번호": "10",
  "거래내역/행10/일자": "2024-10-31",
  "거래내역/행10/품명": "레미콘 25-24-150",
  "거래내역/행10/수량": "38",
  "거래내역/행10/단가": "112,000",
  "거래내역/행10/금액": "4,256,000",
  "거래내역/행10/세액": "425,600",
  "합계/수량": "1635",
  "합계/금액": "64,720,000",
  "합계/세액": "6,472,000",
  "발급자/상호": "동서자재 주식회사",
  "발급자/사업자등록번호": "124-86-35177",
  "발급자/주소": "경기도 화성시 팔탄면 시청로 860",
  "발급자/연락처": "031-352-6700",
  "발급자/대표이사": "강현우"
}
